bennie_bash/__init__.py
bennie_bash/__main__.py
bennie_bash/bennie_bash.py
bennie_bash-0.1.0.dist-info/LICENSE
bennie_bash-0.1.0.dist-info/METADATA
bennie_bash-0.1.0.dist-info/WHEEL
bennie_bash-0.1.0.dist-info/entry_points.txt
bennie_bash-0.1.0.dist-info/top_level.txt
bennie_bash-0.1.0.dist-info/RECORD
