Metadata-Version: 2.1
Name: bennie-bash
Version: 0.1.0
Summary: Personal Bash Shell
Home-page: https://github.com/hunglun/bennie_bash
Download-URL: https://github.com/hunglun/bennie_bash
Author: O Hung Lun
Author-email: hunglun.o@gmail.com
Maintainer: O Hung Lun
Maintainer-email: hunglun.o@gmail.com
License: GNU
Project-URL: Bug Tracker, https://github.com/hunglun/bennie_bash/issues
Keywords: bash,BennieBash
Classifier: Environment :: Console
Classifier: Intended Audience :: Developers
Classifier: Operating System :: POSIX :: Linux
Classifier: Programming Language :: Python :: 3
Requires-Python: >=3.6
License-File: LICENSE
Requires-Dist: pytest
